cdk_slack_chatbot/__init__.py
cdk_slack_chatbot/py.typed
cdk_slack_chatbot/_jsii/__init__.py
cdk_slack_chatbot/_jsii/cdk-slack-chatbot@1.0.198.jsii.tgz
cdk_slack_chatbot-1.0.198.dist-info/LICENSE
cdk_slack_chatbot-1.0.198.dist-info/METADATA
cdk_slack_chatbot-1.0.198.dist-info/WHEEL
cdk_slack_chatbot-1.0.198.dist-info/top_level.txt
cdk_slack_chatbot-1.0.198.dist-info/RECORD
